[{"artist": "MC Frontalot", "album": "Zero Day", "song": "Zero Day"}, {"artist": "YTCracker", "album": "Bitcoin Baron", "song": "Bitcoin Baron"}, {"artist": "Dr. Ackward", "album": "Blank Pages", "song": "High Fives"}, {"artist": "MC Chris", "album": "Race Wars", "song": "Nerd Cave"}, {"artist": "Soup or Villainz", "album": "Villainz For Hire", "song": "Game To Play"}, {"artist": "Wu-Tang Clan", "album": "Forever", "song": "Protect Ya Neck"}, {"artist": "Me", "album": "My First Album", "song": "My first day at HU"}]